Metadata-Version: 2.1
Name: telegram_notification_allure
Version: 0.1
Summary: Notification allure test result for Telegram
Author-email: maxkamtayev@gmail.com
